zacktools/__init__.py
zacktools/pageparser.py
zacktools-0.1.38.dist-info/METADATA
zacktools-0.1.38.dist-info/WHEEL
zacktools-0.1.38.dist-info/top_level.txt
zacktools-0.1.38.dist-info/RECORD
